tennisim/__init__.py
tennisim/game.py
tennisim/match.py
tennisim/set.py
tennisim/sim.py
tennisim/tiebreak.py
tennisim/utils.py
tennisim-0.1.3.dist-info/LICENSE
tennisim-0.1.3.dist-info/WHEEL
tennisim-0.1.3.dist-info/METADATA
tennisim-0.1.3.dist-info/RECORD
