Metadata-Version: 2.1
Name: tennisim
Version: 0.1.3
Summary: Simple pure python functions for simulating tennis matches
Home-page: https://github.com/mjam03/tennisim
License: MIT
Author: Mark Jamison
Author-email: markjamison03@gmail.com
Requires-Python: >=3.7.1,<3.11
Classifier: License :: OSI Approved :: MIT License
Classifier: Programming Language :: Python :: 3
Classifier: Programming Language :: Python :: 3.10
Classifier: Programming Language :: Python :: 3.8
Classifier: Programming Language :: Python :: 3.9
Project-URL: Changelog, https://github.com/mjam03/tennisim/releases
Project-URL: Documentation, https://mjam03.github.io/tennisim
Project-URL: Repository, https://github.com/mjam03/tennisim
